{
  "id": "1:9361",
  "name": "5",
  "type": "TEXT",
  "page": "03-upload-material-selector",
  "platform": "desktop",
  "parent": "1:9359",
  "children": [],
  "layout": {
    "x": 45,
    "y": 11,
    "width": 10,
    "height": 22,
    "constraints": {
      "horizontal": "MIN",
      "vertical": "MIN"
    },
    "autolayout": {
      "direction": "column",
      "justify": "center"
    }
  },
  "style": {
    "css": "className: [word-break:break-word] flex flex-col font-['Bricolage_Grotesque:Medium',sans-serif] font-medium justify-center leading-[0] relative shrink-0 text-[#303030] text-[16px] tracking-[-0.64px] whitespace-nowrap; style: {{",
    "tokenRefs": [
      "text-typographytokens-paragraph-paragraph-primary-medium-500-p3"
    ],
    "typography": {
      "fontFamily": "Bricolage_Grotesque:Medium",
      "size": 16,
      "weight": 500,
      "lineHeight": 0.0,
      "letterSpacing": -0.64
    }
  },
  "assets": [],
  "code": {
    "react": "<div className=\"[word-break:break-word] flex flex-col font-['Bricolage_Grotesque:Medium',sans-serif] font-medium justify-center leading-[0] relative shrink-0 text-[#303030] text-[16px] tracking-[-0.64px] whitespace-nowrap\" data-node-id=\"1:9361\" style={{ fontVariationSettings: \"'opsz' 14, 'wdth' 100\" }}>\n                        <p className=\"leading-[1.4]\">5</p>\n                      </div>"
  }
}